fizicks/__init__.py
fizicks/collision.py
fizicks/data.py
fizicks/main.py
fizicks/matter.py
fizicks/motion.py
fizicks/universe.py
fizicks/util.py
fizicks/visual.py
tests/__init__.py
tests/test_collision.py
tests/test_matter.py
tests/test_motion.py
fizicks-0.2.2.dist-info/LICENSE
fizicks-0.2.2.dist-info/METADATA
fizicks-0.2.2.dist-info/WHEEL
fizicks-0.2.2.dist-info/top_level.txt
fizicks-0.2.2.dist-info/RECORD
