Metadata-Version: 2.1
Name: fizicks
Version: 0.2.2
Summary: A state-driven physics model designed to simulate cause and effect within a physical space.
Home-page: https://pypi.org/project/fizicks/
Author: Chris Mangum
Author-email: csmangum@gmail.com
Classifier: Programming Language :: Python :: 3
Classifier: License :: OSI Approved :: MIT License
Classifier: Operating System :: OS Independent
Requires-Python: >=3.10
License-File: LICENSE
